{"cameraMode":{"drawMode":0,"name":"Shaded","section":"Shading Mode"},"sceneLighting":true,"audioPlay":false,"sceneViewState":{"showFog":true,"showMaterialUpdate":false,"showSkybox":true,"showFlares":true,"showImageEffects":true,"showParticleSystems":true},"in2DMode":false,"pivot":{"x":-77.75291442871094,"y":-272.68023681640627,"z":579.9293212890625},"rotation":{"x":0.2063196897506714,"y":0.07887057214975357,"z":-0.016686687245965005,"w":0.9751580357551575},"size":1107.00732421875,"orthographic":false}